{
  "images": [
    {
      "id": 53,
      "file_name": "tile_321.jpg",
      "width": 500,
      "height": 500
    }
  ],
  "annotations": [
    {
      "id": 0,
      "image_id": 53,
      "category_id": 0,
      "bbox": [
        0,
        0,
        16,
        48
      ],
      "area": 768,
      "iscrowd": 0
    },
    {
      "id": 1,
      "image_id": 53,
      "category_id": 0,
      "bbox": [
        40,
        0,
        72,
        16
      ],
      "area": 1152,
      "iscrowd": 0
    },
    {
      "id": 2,
      "image_id": 53,
      "category_id": 0,
      "bbox": [
        136,
        0,
        72,
        34
      ],
      "area": 2448,
      "iscrowd": 0
    },
    {
      "id": 3,
      "image_id": 53,
      "category_id": 0,
      "bbox": [
        216,
        0,
        72,
        16
      ],
      "area": 1152,
      "iscrowd": 0
    },
    {
      "id": 4,
      "image_id": 53,
      "category_id": 0,
      "bbox": [
        296,
        0,
        204,
        500
      ],
      "area": 102000,
      "iscrowd": 0
    },
    {
      "id": 5,
      "image_id": 53,
      "category_id": 0,
      "bbox": [
        225,
        11,
        1,
        2
      ],
      "area": 2,
      "iscrowd": 0
    },
    {
      "id": 6,
      "image_id": 53,
      "category_id": 0,
      "bbox": [
        220,
        12,
        3,
        4
      ],
      "area": 12,
      "iscrowd": 0
    },
    {
      "id": 7,
      "image_id": 53,
      "category_id": 0,
      "bbox": [
        56,
        15,
        1,
        1
      ],
      "area": 1,
      "iscrowd": 0
    },
    {
      "id": 8,
      "image_id": 53,
      "category_id": 0,
      "bbox": [
        216,
        14,
        1,
        2
      ],
      "area": 2,
      "iscrowd": 0
    },
    {
      "id": 9,
      "image_id": 53,
      "category_id": 0,
      "bbox": [
        224,
        14,
        3,
        2
      ],
      "area": 6,
      "iscrowd": 0
    },
    {
      "id": 10,
      "image_id": 53,
      "category_id": 0,
      "bbox": [
        231,
        14,
        2,
        2
      ],
      "area": 4,
      "iscrowd": 0
    },
    {
      "id": 11,
      "image_id": 53,
      "category_id": 0,
      "bbox": [
        234,
        14,
        4,
        2
      ],
      "area": 8,
      "iscrowd": 0
    },
    {
      "id": 12,
      "image_id": 53,
      "category_id": 0,
      "bbox": [
        283,
        15,
        1,
        1
      ],
      "area": 1,
      "iscrowd": 0
    },
    {
      "id": 13,
      "image_id": 53,
      "category_id": 0,
      "bbox": [
        136,
        31,
        1,
        1
      ],
      "area": 1,
      "iscrowd": 0
    },
    {
      "id": 14,
      "image_id": 53,
      "category_id": 0,
      "bbox": [
        48,
        56,
        8,
        1
      ],
      "area": 8,
      "iscrowd": 0
    },
    {
      "id": 15,
      "image_id": 53,
      "category_id": 0,
      "bbox": [
        48,
        58,
        8,
        2
      ],
      "area": 16,
      "iscrowd": 0
    },
    {
      "id": 16,
      "image_id": 53,
      "category_id": 0,
      "bbox": [
        48,
        62,
        8,
        1
      ],
      "area": 8,
      "iscrowd": 0
    },
    {
      "id": 17,
      "image_id": 53,
      "category_id": 0,
      "bbox": [
        216,
        64,
        1,
        2
      ],
      "area": 2,
      "iscrowd": 0
    },
    {
      "id": 18,
      "image_id": 53,
      "category_id": 0,
      "bbox": [
        208,
        64,
        80,
        96
      ],
      "area": 7680,
      "iscrowd": 0
    },
    {
      "id": 19,
      "image_id": 53,
      "category_id": 0,
      "bbox": [
        216,
        68,
        1,
        1
      ],
      "area": 1,
      "iscrowd": 0
    },
    {
      "id": 20,
      "image_id": 53,
      "category_id": 0,
      "bbox": [
        48,
        72,
        1,
        1
      ],
      "area": 1,
      "iscrowd": 0
    },
    {
      "id": 21,
      "image_id": 53,
      "category_id": 0,
      "bbox": [
        48,
        72,
        64,
        58
      ],
      "area": 3712,
      "iscrowd": 0
    },
    {
      "id": 22,
      "image_id": 53,
      "category_id": 0,
      "bbox": [
        128,
        72,
        72,
        88
      ],
      "area": 6336,
      "iscrowd": 0
    },
    {
      "id": 23,
      "image_id": 53,
      "category_id": 0,
      "bbox": [
        199,
        72,
        1,
        1
      ],
      "area": 1,
      "iscrowd": 0
    },
    {
      "id": 24,
      "image_id": 53,
      "category_id": 0,
      "bbox": [
        208,
        72,
        1,
        2
      ],
      "area": 2,
      "iscrowd": 0
    },
    {
      "id": 25,
      "image_id": 53,
      "category_id": 0,
      "bbox": [
        208,
        72,
        5,
        6
      ],
      "area": 30,
      "iscrowd": 0
    },
    {
      "id": 26,
      "image_id": 53,
      "category_id": 0,
      "bbox": [
        208,
        79,
        1,
        1
      ],
      "area": 1,
      "iscrowd": 0
    },
    {
      "id": 27,
      "image_id": 53,
      "category_id": 0,
      "bbox": [
        0,
        80,
        10,
        2
      ],
      "area": 20,
      "iscrowd": 0
    },
    {
      "id": 28,
      "image_id": 53,
      "category_id": 0,
      "bbox": [
        11,
        80,
        1,
        1
      ],
      "area": 1,
      "iscrowd": 0
    },
    {
      "id": 29,
      "image_id": 53,
      "category_id": 0,
      "bbox": [
        0,
        80,
        16,
        80
      ],
      "area": 1280,
      "iscrowd": 0
    },
    {
      "id": 30,
      "image_id": 53,
      "category_id": 0,
      "bbox": [
        208,
        80,
        5,
        32
      ],
      "area": 160,
      "iscrowd": 0
    },
    {
      "id": 31,
      "image_id": 53,
      "category_id": 0,
      "bbox": [
        15,
        104,
        1,
        1
      ],
      "area": 1,
      "iscrowd": 0
    },
    {
      "id": 32,
      "image_id": 53,
      "category_id": 0,
      "bbox": [
        14,
        106,
        1,
        4
      ],
      "area": 4,
      "iscrowd": 0
    },
    {
      "id": 33,
      "image_id": 53,
      "category_id": 0,
      "bbox": [
        128,
        108,
        1,
        2
      ],
      "area": 2,
      "iscrowd": 0
    },
    {
      "id": 34,
      "image_id": 53,
      "category_id": 0,
      "bbox": [
        15,
        125,
        1,
        3
      ],
      "area": 3,
      "iscrowd": 0
    },
    {
      "id": 35,
      "image_id": 53,
      "category_id": 0,
      "bbox": [
        15,
        130,
        1,
        3
      ],
      "area": 3,
      "iscrowd": 0
    },
    {
      "id": 36,
      "image_id": 53,
      "category_id": 0,
      "bbox": [
        96,
        133,
        8,
        2
      ],
      "area": 16,
      "iscrowd": 0
    },
    {
      "id": 37,
      "image_id": 53,
      "category_id": 0,
      "bbox": [
        15,
        136,
        1,
        8
      ],
      "area": 8,
      "iscrowd": 0
    },
    {
      "id": 38,
      "image_id": 53,
      "category_id": 0,
      "bbox": [
        198,
        137,
        2,
        18
      ],
      "area": 36,
      "iscrowd": 0
    },
    {
      "id": 39,
      "image_id": 53,
      "category_id": 0,
      "bbox": [
        152,
        151,
        1,
        1
      ],
      "area": 1,
      "iscrowd": 0
    },
    {
      "id": 40,
      "image_id": 53,
      "category_id": 0,
      "bbox": [
        15,
        153,
        1,
        2
      ],
      "area": 2,
      "iscrowd": 0
    },
    {
      "id": 41,
      "image_id": 53,
      "category_id": 0,
      "bbox": [
        13,
        155,
        3,
        5
      ],
      "area": 15,
      "iscrowd": 0
    },
    {
      "id": 42,
      "image_id": 53,
      "category_id": 0,
      "bbox": [
        176,
        155,
        12,
        5
      ],
      "area": 60,
      "iscrowd": 0
    },
    {
      "id": 43,
      "image_id": 53,
      "category_id": 0,
      "bbox": [
        197,
        156,
        3,
        4
      ],
      "area": 12,
      "iscrowd": 0
    },
    {
      "id": 44,
      "image_id": 53,
      "category_id": 0,
      "bbox": [
        195,
        159,
        2,
        1
      ],
      "area": 2,
      "iscrowd": 0
    },
    {
      "id": 45,
      "image_id": 53,
      "category_id": 0,
      "bbox": [
        276,
        159,
        3,
        1
      ],
      "area": 3,
      "iscrowd": 0
    },
    {
      "id": 46,
      "image_id": 53,
      "category_id": 0,
      "bbox": [
        280,
        159,
        2,
        1
      ],
      "area": 2,
      "iscrowd": 0
    },
    {
      "id": 47,
      "image_id": 53,
      "category_id": 0,
      "bbox": [
        192,
        171,
        8,
        2
      ],
      "area": 16,
      "iscrowd": 0
    },
    {
      "id": 48,
      "image_id": 53,
      "category_id": 0,
      "bbox": [
        209,
        176,
        4,
        3
      ],
      "area": 12,
      "iscrowd": 0
    },
    {
      "id": 49,
      "image_id": 53,
      "category_id": 0,
      "bbox": [
        208,
        176,
        72,
        80
      ],
      "area": 5760,
      "iscrowd": 0
    },
    {
      "id": 50,
      "image_id": 53,
      "category_id": 0,
      "bbox": [
        272,
        176,
        1,
        1
      ],
      "area": 1,
      "iscrowd": 0
    },
    {
      "id": 51,
      "image_id": 53,
      "category_id": 0,
      "bbox": [
        275,
        176,
        3,
        1
      ],
      "area": 3,
      "iscrowd": 0
    },
    {
      "id": 52,
      "image_id": 53,
      "category_id": 0,
      "bbox": [
        0,
        184,
        16,
        88
      ],
      "area": 1408,
      "iscrowd": 0
    },
    {
      "id": 53,
      "image_id": 53,
      "category_id": 0,
      "bbox": [
        12,
        184,
        2,
        1
      ],
      "area": 2,
      "iscrowd": 0
    },
    {
      "id": 54,
      "image_id": 53,
      "category_id": 0,
      "bbox": [
        32,
        184,
        4,
        2
      ],
      "area": 8,
      "iscrowd": 0
    },
    {
      "id": 55,
      "image_id": 53,
      "category_id": 0,
      "bbox": [
        32,
        184,
        80,
        104
      ],
      "area": 8320,
      "iscrowd": 0
    },
    {
      "id": 56,
      "image_id": 53,
      "category_id": 0,
      "bbox": [
        92,
        184,
        2,
        1
      ],
      "area": 2,
      "iscrowd": 0
    },
    {
      "id": 57,
      "image_id": 53,
      "category_id": 0,
      "bbox": [
        108,
        184,
        1,
        1
      ],
      "area": 1,
      "iscrowd": 0
    },
    {
      "id": 58,
      "image_id": 53,
      "category_id": 0,
      "bbox": [
        128,
        184,
        64,
        102
      ],
      "area": 6528,
      "iscrowd": 0
    },
    {
      "id": 59,
      "image_id": 53,
      "category_id": 0,
      "bbox": [
        185,
        184,
        2,
        3
      ],
      "area": 6,
      "iscrowd": 0
    },
    {
      "id": 60,
      "image_id": 53,
      "category_id": 0,
      "bbox": [
        279,
        189,
        1,
        1
      ],
      "area": 1,
      "iscrowd": 0
    },
    {
      "id": 61,
      "image_id": 53,
      "category_id": 0,
      "bbox": [
        111,
        191,
        1,
        9
      ],
      "area": 9,
      "iscrowd": 0
    },
    {
      "id": 62,
      "image_id": 53,
      "category_id": 0,
      "bbox": [
        365,
        193,
        1,
        4
      ],
      "area": 4,
      "iscrowd": 0
    },
    {
      "id": 63,
      "image_id": 53,
      "category_id": 0,
      "bbox": [
        367,
        192,
        1,
        1
      ],
      "area": 1,
      "iscrowd": 0
    },
    {
      "id": 64,
      "image_id": 53,
      "category_id": 0,
      "bbox": [
        32,
        201,
        2,
        9
      ],
      "area": 18,
      "iscrowd": 0
    },
    {
      "id": 65,
      "image_id": 53,
      "category_id": 0,
      "bbox": [
        208,
        203,
        1,
        2
      ],
      "area": 2,
      "iscrowd": 0
    },
    {
      "id": 66,
      "image_id": 53,
      "category_id": 0,
      "bbox": [
        296,
        206,
        1,
        2
      ],
      "area": 2,
      "iscrowd": 0
    },
    {
      "id": 67,
      "image_id": 53,
      "category_id": 0,
      "bbox": [
        190,
        210,
        2,
        4
      ],
      "area": 8,
      "iscrowd": 0
    },
    {
      "id": 68,
      "image_id": 53,
      "category_id": 0,
      "bbox": [
        211,
        211,
        2,
        3
      ],
      "area": 6,
      "iscrowd": 0
    },
    {
      "id": 69,
      "image_id": 53,
      "category_id": 0,
      "bbox": [
        208,
        212,
        5,
        36
      ],
      "area": 180,
      "iscrowd": 0
    },
    {
      "id": 70,
      "image_id": 53,
      "category_id": 0,
      "bbox": [
        32,
        216,
        1,
        6
      ],
      "area": 6,
      "iscrowd": 0
    },
    {
      "id": 71,
      "image_id": 53,
      "category_id": 0,
      "bbox": [
        128,
        224,
        1,
        3
      ],
      "area": 3,
      "iscrowd": 0
    },
    {
      "id": 72,
      "image_id": 53,
      "category_id": 0,
      "bbox": [
        32,
        228,
        1,
        4
      ],
      "area": 4,
      "iscrowd": 0
    },
    {
      "id": 73,
      "image_id": 53,
      "category_id": 0,
      "bbox": [
        111,
        240,
        1,
        8
      ],
      "area": 8,
      "iscrowd": 0
    },
    {
      "id": 74,
      "image_id": 53,
      "category_id": 0,
      "bbox": [
        32,
        245,
        2,
        27
      ],
      "area": 54,
      "iscrowd": 0
    },
    {
      "id": 75,
      "image_id": 53,
      "category_id": 0,
      "bbox": [
        248,
        251,
        2,
        2
      ],
      "area": 4,
      "iscrowd": 0
    },
    {
      "id": 76,
      "image_id": 53,
      "category_id": 0,
      "bbox": [
        279,
        251,
        1,
        3
      ],
      "area": 3,
      "iscrowd": 0
    },
    {
      "id": 77,
      "image_id": 53,
      "category_id": 0,
      "bbox": [
        232,
        253,
        8,
        2
      ],
      "area": 16,
      "iscrowd": 0
    },
    {
      "id": 78,
      "image_id": 53,
      "category_id": 0,
      "bbox": [
        248,
        253,
        12,
        3
      ],
      "area": 36,
      "iscrowd": 0
    },
    {
      "id": 79,
      "image_id": 53,
      "category_id": 0,
      "bbox": [
        264,
        255,
        1,
        1
      ],
      "area": 1,
      "iscrowd": 0
    },
    {
      "id": 80,
      "image_id": 53,
      "category_id": 0,
      "bbox": [
        278,
        255,
        1,
        1
      ],
      "area": 1,
      "iscrowd": 0
    },
    {
      "id": 81,
      "image_id": 53,
      "category_id": 0,
      "bbox": [
        14,
        267,
        2,
        1
      ],
      "area": 2,
      "iscrowd": 0
    },
    {
      "id": 82,
      "image_id": 53,
      "category_id": 0,
      "bbox": [
        11,
        269,
        4,
        3
      ],
      "area": 12,
      "iscrowd": 0
    },
    {
      "id": 83,
      "image_id": 53,
      "category_id": 0,
      "bbox": [
        1,
        270,
        5,
        2
      ],
      "area": 10,
      "iscrowd": 0
    },
    {
      "id": 84,
      "image_id": 53,
      "category_id": 0,
      "bbox": [
        15,
        271,
        1,
        1
      ],
      "area": 1,
      "iscrowd": 0
    },
    {
      "id": 85,
      "image_id": 53,
      "category_id": 0,
      "bbox": [
        128,
        276,
        4,
        4
      ],
      "area": 16,
      "iscrowd": 0
    },
    {
      "id": 86,
      "image_id": 53,
      "category_id": 0,
      "bbox": [
        191,
        279,
        1,
        1
      ],
      "area": 1,
      "iscrowd": 0
    },
    {
      "id": 87,
      "image_id": 53,
      "category_id": 0,
      "bbox": [
        0,
        280,
        8,
        7
      ],
      "area": 56,
      "iscrowd": 0
    },
    {
      "id": 88,
      "image_id": 53,
      "category_id": 0,
      "bbox": [
        6,
        287,
        2,
        1
      ],
      "area": 2,
      "iscrowd": 0
    },
    {
      "id": 89,
      "image_id": 53,
      "category_id": 0,
      "bbox": [
        32,
        287,
        1,
        1
      ],
      "area": 1,
      "iscrowd": 0
    },
    {
      "id": 90,
      "image_id": 53,
      "category_id": 0,
      "bbox": [
        99,
        287,
        3,
        1
      ],
      "area": 3,
      "iscrowd": 0
    },
    {
      "id": 91,
      "image_id": 53,
      "category_id": 0,
      "bbox": [
        103,
        287,
        3,
        1
      ],
      "area": 3,
      "iscrowd": 0
    },
    {
      "id": 92,
      "image_id": 53,
      "category_id": 0,
      "bbox": [
        111,
        287,
        1,
        1
      ],
      "area": 1,
      "iscrowd": 0
    },
    {
      "id": 93,
      "image_id": 53,
      "category_id": 0,
      "bbox": [
        154,
        287,
        1,
        1
      ],
      "area": 1,
      "iscrowd": 0
    },
    {
      "id": 94,
      "image_id": 53,
      "category_id": 0,
      "bbox": [
        40,
        296,
        1,
        1
      ],
      "area": 1,
      "iscrowd": 0
    },
    {
      "id": 95,
      "image_id": 53,
      "category_id": 0,
      "bbox": [
        40,
        296,
        80,
        88
      ],
      "area": 7040,
      "iscrowd": 0
    },
    {
      "id": 96,
      "image_id": 53,
      "category_id": 0,
      "bbox": [
        53,
        296,
        7,
        1
      ],
      "area": 7,
      "iscrowd": 0
    },
    {
      "id": 97,
      "image_id": 53,
      "category_id": 0,
      "bbox": [
        79,
        296,
        1,
        1
      ],
      "area": 1,
      "iscrowd": 0
    },
    {
      "id": 98,
      "image_id": 53,
      "category_id": 0,
      "bbox": [
        96,
        296,
        2,
        1
      ],
      "area": 2,
      "iscrowd": 0
    },
    {
      "id": 99,
      "image_id": 53,
      "category_id": 0,
      "bbox": [
        101,
        296,
        1,
        1
      ],
      "area": 1,
      "iscrowd": 0
    },
    {
      "id": 100,
      "image_id": 53,
      "category_id": 0,
      "bbox": [
        136,
        296,
        2,
        1
      ],
      "area": 2,
      "iscrowd": 0
    },
    {
      "id": 101,
      "image_id": 53,
      "category_id": 0,
      "bbox": [
        136,
        296,
        64,
        80
      ],
      "area": 5120,
      "iscrowd": 0
    },
    {
      "id": 102,
      "image_id": 53,
      "category_id": 0,
      "bbox": [
        165,
        296,
        3,
        1
      ],
      "area": 3,
      "iscrowd": 0
    },
    {
      "id": 103,
      "image_id": 53,
      "category_id": 0,
      "bbox": [
        216,
        296,
        64,
        88
      ],
      "area": 5632,
      "iscrowd": 0
    },
    {
      "id": 104,
      "image_id": 53,
      "category_id": 0,
      "bbox": [
        230,
        296,
        1,
        1
      ],
      "area": 1,
      "iscrowd": 0
    },
    {
      "id": 105,
      "image_id": 53,
      "category_id": 0,
      "bbox": [
        236,
        296,
        4,
        1
      ],
      "area": 4,
      "iscrowd": 0
    },
    {
      "id": 106,
      "image_id": 53,
      "category_id": 0,
      "bbox": [
        367,
        297,
        1,
        3
      ],
      "area": 3,
      "iscrowd": 0
    },
    {
      "id": 107,
      "image_id": 53,
      "category_id": 0,
      "bbox": [
        103,
        298,
        1,
        1
      ],
      "area": 1,
      "iscrowd": 0
    },
    {
      "id": 108,
      "image_id": 53,
      "category_id": 0,
      "bbox": [
        138,
        298,
        3,
        2
      ],
      "area": 6,
      "iscrowd": 0
    },
    {
      "id": 109,
      "image_id": 53,
      "category_id": 0,
      "bbox": [
        102,
        300,
        2,
        1
      ],
      "area": 2,
      "iscrowd": 0
    },
    {
      "id": 110,
      "image_id": 53,
      "category_id": 0,
      "bbox": [
        196,
        301,
        2,
        1
      ],
      "area": 2,
      "iscrowd": 0
    },
    {
      "id": 111,
      "image_id": 53,
      "category_id": 0,
      "bbox": [
        300,
        303,
        2,
        1
      ],
      "area": 2,
      "iscrowd": 0
    },
    {
      "id": 112,
      "image_id": 53,
      "category_id": 0,
      "bbox": [
        361,
        303,
        3,
        1
      ],
      "area": 3,
      "iscrowd": 0
    },
    {
      "id": 113,
      "image_id": 53,
      "category_id": 0,
      "bbox": [
        0,
        312,
        7,
        2
      ],
      "area": 14,
      "iscrowd": 0
    },
    {
      "id": 114,
      "image_id": 53,
      "category_id": 0,
      "bbox": [
        9,
        312,
        1,
        1
      ],
      "area": 1,
      "iscrowd": 0
    },
    {
      "id": 115,
      "image_id": 53,
      "category_id": 0,
      "bbox": [
        10,
        312,
        2,
        3
      ],
      "area": 6,
      "iscrowd": 0
    },
    {
      "id": 116,
      "image_id": 53,
      "category_id": 0,
      "bbox": [
        14,
        312,
        2,
        1
      ],
      "area": 2,
      "iscrowd": 0
    },
    {
      "id": 117,
      "image_id": 53,
      "category_id": 0,
      "bbox": [
        40,
        312,
        1,
        11
      ],
      "area": 11,
      "iscrowd": 0
    },
    {
      "id": 118,
      "image_id": 53,
      "category_id": 0,
      "bbox": [
        0,
        314,
        16,
        62
      ],
      "area": 992,
      "iscrowd": 0
    },
    {
      "id": 119,
      "image_id": 53,
      "category_id": 0,
      "bbox": [
        198,
        320,
        1,
        4
      ],
      "area": 4,
      "iscrowd": 0
    },
    {
      "id": 120,
      "image_id": 53,
      "category_id": 0,
      "bbox": [
        41,
        367,
        1,
        1
      ],
      "area": 1,
      "iscrowd": 0
    },
    {
      "id": 121,
      "image_id": 53,
      "category_id": 0,
      "bbox": [
        15,
        375,
        1,
        1
      ],
      "area": 1,
      "iscrowd": 0
    },
    {
      "id": 122,
      "image_id": 53,
      "category_id": 0,
      "bbox": [
        115,
        378,
        2,
        1
      ],
      "area": 2,
      "iscrowd": 0
    },
    {
      "id": 123,
      "image_id": 53,
      "category_id": 0,
      "bbox": [
        216,
        379,
        1,
        1
      ],
      "area": 1,
      "iscrowd": 0
    },
    {
      "id": 124,
      "image_id": 53,
      "category_id": 0,
      "bbox": [
        40,
        381,
        3,
        3
      ],
      "area": 9,
      "iscrowd": 0
    },
    {
      "id": 125,
      "image_id": 53,
      "category_id": 0,
      "bbox": [
        216,
        382,
        3,
        2
      ],
      "area": 6,
      "iscrowd": 0
    },
    {
      "id": 126,
      "image_id": 53,
      "category_id": 0,
      "bbox": [
        96,
        393,
        8,
        3
      ],
      "area": 24,
      "iscrowd": 0
    },
    {
      "id": 127,
      "image_id": 53,
      "category_id": 0,
      "bbox": [
        216,
        392,
        80,
        80
      ],
      "area": 6400,
      "iscrowd": 0
    },
    {
      "id": 128,
      "image_id": 53,
      "category_id": 0,
      "bbox": [
        263,
        392,
        1,
        1
      ],
      "area": 1,
      "iscrowd": 0
    },
    {
      "id": 129,
      "image_id": 53,
      "category_id": 0,
      "bbox": [
        216,
        395,
        2,
        30
      ],
      "area": 60,
      "iscrowd": 0
    },
    {
      "id": 130,
      "image_id": 53,
      "category_id": 0,
      "bbox": [
        278,
        394,
        2,
        2
      ],
      "area": 4,
      "iscrowd": 0
    },
    {
      "id": 131,
      "image_id": 53,
      "category_id": 0,
      "bbox": [
        96,
        398,
        8,
        2
      ],
      "area": 16,
      "iscrowd": 0
    },
    {
      "id": 132,
      "image_id": 53,
      "category_id": 0,
      "bbox": [
        0,
        401,
        3,
        5
      ],
      "area": 15,
      "iscrowd": 0
    },
    {
      "id": 133,
      "image_id": 53,
      "category_id": 0,
      "bbox": [
        0,
        400,
        24,
        96
      ],
      "area": 2304,
      "iscrowd": 0
    },
    {
      "id": 134,
      "image_id": 53,
      "category_id": 0,
      "bbox": [
        23,
        403,
        1,
        4
      ],
      "area": 4,
      "iscrowd": 0
    },
    {
      "id": 135,
      "image_id": 53,
      "category_id": 0,
      "bbox": [
        96,
        408,
        12,
        3
      ],
      "area": 36,
      "iscrowd": 0
    },
    {
      "id": 136,
      "image_id": 53,
      "category_id": 0,
      "bbox": [
        105,
        408,
        2,
        1
      ],
      "area": 2,
      "iscrowd": 0
    },
    {
      "id": 137,
      "image_id": 53,
      "category_id": 0,
      "bbox": [
        40,
        408,
        88,
        88
      ],
      "area": 7744,
      "iscrowd": 0
    },
    {
      "id": 138,
      "image_id": 53,
      "category_id": 0,
      "bbox": [
        136,
        409,
        1,
        1
      ],
      "area": 1,
      "iscrowd": 0
    },
    {
      "id": 139,
      "image_id": 53,
      "category_id": 0,
      "bbox": [
        138,
        408,
        2,
        2
      ],
      "area": 4,
      "iscrowd": 0
    },
    {
      "id": 140,
      "image_id": 53,
      "category_id": 0,
      "bbox": [
        136,
        408,
        72,
        88
      ],
      "area": 6336,
      "iscrowd": 0
    },
    {
      "id": 141,
      "image_id": 53,
      "category_id": 0,
      "bbox": [
        199,
        408,
        1,
        1
      ],
      "area": 1,
      "iscrowd": 0
    },
    {
      "id": 142,
      "image_id": 53,
      "category_id": 0,
      "bbox": [
        23,
        410,
        1,
        3
      ],
      "area": 3,
      "iscrowd": 0
    },
    {
      "id": 143,
      "image_id": 53,
      "category_id": 0,
      "bbox": [
        97,
        410,
        6,
        3
      ],
      "area": 18,
      "iscrowd": 0
    },
    {
      "id": 144,
      "image_id": 53,
      "category_id": 0,
      "bbox": [
        127,
        415,
        1,
        2
      ],
      "area": 2,
      "iscrowd": 0
    },
    {
      "id": 145,
      "image_id": 53,
      "category_id": 0,
      "bbox": [
        40,
        416,
        1,
        1
      ],
      "area": 1,
      "iscrowd": 0
    },
    {
      "id": 146,
      "image_id": 53,
      "category_id": 0,
      "bbox": [
        126,
        423,
        2,
        9
      ],
      "area": 18,
      "iscrowd": 0
    },
    {
      "id": 147,
      "image_id": 53,
      "category_id": 0,
      "bbox": [
        40,
        425,
        1,
        3
      ],
      "area": 3,
      "iscrowd": 0
    },
    {
      "id": 148,
      "image_id": 53,
      "category_id": 0,
      "bbox": [
        136,
        424,
        1,
        8
      ],
      "area": 8,
      "iscrowd": 0
    },
    {
      "id": 149,
      "image_id": 53,
      "category_id": 0,
      "bbox": [
        23,
        427,
        1,
        2
      ],
      "area": 2,
      "iscrowd": 0
    },
    {
      "id": 150,
      "image_id": 53,
      "category_id": 0,
      "bbox": [
        40,
        430,
        1,
        2
      ],
      "area": 2,
      "iscrowd": 0
    },
    {
      "id": 151,
      "image_id": 53,
      "category_id": 0,
      "bbox": [
        126,
        440,
        1,
        16
      ],
      "area": 16,
      "iscrowd": 0
    },
    {
      "id": 152,
      "image_id": 53,
      "category_id": 0,
      "bbox": [
        136,
        448,
        1,
        8
      ],
      "area": 8,
      "iscrowd": 0
    },
    {
      "id": 153,
      "image_id": 53,
      "category_id": 0,
      "bbox": [
        126,
        464,
        2,
        18
      ],
      "area": 36,
      "iscrowd": 0
    },
    {
      "id": 154,
      "image_id": 53,
      "category_id": 0,
      "bbox": [
        295,
        467,
        1,
        2
      ],
      "area": 2,
      "iscrowd": 0
    },
    {
      "id": 155,
      "image_id": 53,
      "category_id": 0,
      "bbox": [
        278,
        471,
        5,
        1
      ],
      "area": 5,
      "iscrowd": 0
    },
    {
      "id": 156,
      "image_id": 53,
      "category_id": 0,
      "bbox": [
        292,
        471,
        1,
        1
      ],
      "area": 1,
      "iscrowd": 0
    },
    {
      "id": 157,
      "image_id": 53,
      "category_id": 0,
      "bbox": [
        294,
        470,
        2,
        2
      ],
      "area": 4,
      "iscrowd": 0
    },
    {
      "id": 158,
      "image_id": 53,
      "category_id": 0,
      "bbox": [
        136,
        472,
        1,
        8
      ],
      "area": 8,
      "iscrowd": 0
    },
    {
      "id": 159,
      "image_id": 53,
      "category_id": 0,
      "bbox": [
        207,
        479,
        1,
        1
      ],
      "area": 1,
      "iscrowd": 0
    },
    {
      "id": 160,
      "image_id": 53,
      "category_id": 0,
      "bbox": [
        126,
        483,
        2,
        4
      ],
      "area": 8,
      "iscrowd": 0
    },
    {
      "id": 161,
      "image_id": 53,
      "category_id": 0,
      "bbox": [
        127,
        491,
        1,
        1
      ],
      "area": 1,
      "iscrowd": 0
    },
    {
      "id": 162,
      "image_id": 53,
      "category_id": 0,
      "bbox": [
        170,
        491,
        14,
        5
      ],
      "area": 70,
      "iscrowd": 0
    },
    {
      "id": 163,
      "image_id": 53,
      "category_id": 0,
      "bbox": [
        0,
        492,
        17,
        2
      ],
      "area": 34,
      "iscrowd": 0
    },
    {
      "id": 164,
      "image_id": 53,
      "category_id": 0,
      "bbox": [
        22,
        492,
        2,
        1
      ],
      "area": 2,
      "iscrowd": 0
    },
    {
      "id": 165,
      "image_id": 53,
      "category_id": 0,
      "bbox": [
        17,
        495,
        1,
        1
      ],
      "area": 1,
      "iscrowd": 0
    },
    {
      "id": 166,
      "image_id": 53,
      "category_id": 0,
      "bbox": [
        23,
        494,
        1,
        1
      ],
      "area": 1,
      "iscrowd": 0
    },
    {
      "id": 167,
      "image_id": 53,
      "category_id": 0,
      "bbox": [
        67,
        495,
        3,
        1
      ],
      "area": 3,
      "iscrowd": 0
    },
    {
      "id": 168,
      "image_id": 53,
      "category_id": 0,
      "bbox": [
        71,
        494,
        4,
        2
      ],
      "area": 8,
      "iscrowd": 0
    },
    {
      "id": 169,
      "image_id": 53,
      "category_id": 0,
      "bbox": [
        126,
        494,
        2,
        1
      ],
      "area": 2,
      "iscrowd": 0
    },
    {
      "id": 170,
      "image_id": 53,
      "category_id": 0,
      "bbox": [
        143,
        495,
        1,
        1
      ],
      "area": 1,
      "iscrowd": 0
    }
  ],
  "categories": [
    {
      "id": 0,
      "name": "Kanji"
    }
  ]
}